alg_types/__init__.py
alg_types-0.1.2.dist-info/METADATA
alg_types-0.1.2.dist-info/WHEEL
alg_types-0.1.2.dist-info/RECORD
