Metadata-Version: 2.1
Name: alg_types
Version: 0.1.2
Summary: a library to implement rust like enums
Home-page: https://github.com/ayushashi11/alg_types
Author: Prabhakar Dev
Author-email: ayushashi11@gmail.com
Requires-Python: >=3.10,<4.0
Classifier: Programming Language :: Python :: 3
Classifier: Programming Language :: Python :: 3.10
Classifier: Programming Language :: Python :: 3.11
Classifier: Programming Language :: Python :: 3.12
Project-URL: Repository, https://github.com/ayushashi11/alg_types
